MANIFEST.in
setup.py
dueros/__init__.py
dueros/dueros.py
dueros.egg-info/PKG-INFO
dueros.egg-info/SOURCES.txt
dueros.egg-info/dependency_links.txt
dueros.egg-info/top_level.txt