Metadata-Version: 1.1
Name: dueros
Version: 0.0.1
Summary: Testing API
Home-page: UNKNOWN
Author: dialog manager
Author-email: dialogbot@163.com
License: MIT
Keywords: dueros,api
Platform: UNKNOWN
Classifier: Development Status :: 4 - Beta
Classifier: Programming Language :: Python :: 2.7
Classifier: Programming Language :: Python :: 3
Classifier: Topic :: Scientific/Engineering
Classifier: Topic :: Software Development
Classifier: Topic :: Scientific/Engineering :: Artificial Intelligence
